{"type":"Topology","objects":{"tracts":{"type":"GeometryCollection","geometries":[{"type":"Polygon","arcs":[[0,1,2]],"properties":{"GEOID":"55101002402"}},{"type":"Polygon","arcs":[[3,4,5,6,7,8]],"properties":{"GEOID":"55101001101"}},{"type":"Polygon","arcs":[[9,10,11]],"properties":{"GEOID":"55101001505"}},{"type":"Polygon","arcs":[[12,13,14,15,16,17]],"properties":{"GEOID":"55101001705"}},{"type":"Polygon","arcs":[[-7,18,19,20]],"properties":{"GEOID":"55101001002"}},{"type":"Polygon","arcs":[[21,-11,22,23,24,25]],"properties":{"GEOID":"55101001402"}},{"type":"Polygon","arcs":[[26,-25,27,28]],"properties":{"GEOID":"55101001301"}},{"type":"Polygon","arcs":[[29,30,31,32,33]],"properties":{"GEOID":"55101001501"}},{"type":"Polygon","arcs":[[-8,-21,34,35]],"properties":{"GEOID":"55101001001"}},{"type":"Polygon","arcs":[[36,37,38,39,40]],"properties":{"GEOID":"55101000500"}},{"type":"Polygon","arcs":[[-32,41,42,43]],"properties":{"GEOID":"55101001506"}},{"type":"Polygon","arcs":[[44,-35,-20,45,46,47,48,49,50]],"properties":{"GEOID":"55101000901"}},{"type":"Polygon","arcs":[[51,-33,-44,52,53]],"properties":{"GEOID":"55101001507"}},{"type":"Polygon","arcs":[[-17,54,-9,55,56]],"properties":{"GEOID":"55101001706"}},{"type":"Polygon","arcs":[[57,58,59]],"properties":{"GEOID":"55101001702"}},{"type":"Polygon","arcs":[[-53,60,-29,61,62,-14,63]],"properties":{"GEOID":"55101001201"}},{"type":"Polygon","arcs":[[64,-34,-52,65,66,67]],"properties":{"GEOID":"55101001601"}},{"type":"Polygon","arcs":[[68,-49,69,70,71,72]],"properties":{"GEOID":"55101000800"}},{"type":"Polygon","arcs":[[73,-67,-18,-57,-60,74,75]],"properties":{"GEOID":"55101001703"}},{"type":"Polygon","arcs":[[-6,76,-46,-19]],"properties":{"GEOID":"55101001003"}},{"type":"Polygon","arcs":[[77,78,79,80]],"properties":{"GEOID":"55101001801"}},{"type":"Polygon","arcs":[[-31,81,-12,-22,82,-42]],"properties":{"GEOID":"55101001504"}},{"type":"Polygon","arcs":[[-54,-64,-13,-66]],"properties":{"GEOID":"55101001602"}},{"type":"Polygon","arcs":[[83,-41,84,-47,-77,-5,85]],"properties":{"GEOID":"55101000600"}},{"type":"Polygon","arcs":[[-56,-36,-45,86,87,-58]],"properties":{"GEOID":"55101001701"}},{"type":"Polygon","arcs":[[88,89,90,-38,91]],"properties":{"GEOID":"55101000400"}},{"type":"Polygon","arcs":[[-85,-40,92,-70,-48]],"properties":{"GEOID":"55101000700"}},{"type":"Polygon","arcs":[[93,-68,-74,94,95]],"properties":{"GEOID":"55101001900"}},{"type":"Polygon","arcs":[[96,-3,97,98]],"properties":{"GEOID":"55101002401"}},{"type":"Polygon","arcs":[[-98,-2,99,100,101]],"properties":{"GEOID":"55101002600"}},{"type":"Polygon","arcs":[[-16,102,-86,-4,-55]],"properties":{"GEOID":"55101001102"}},{"type":"Polygon","arcs":[[-39,-91,103,104,-71,-93]],"properties":{"GEOID":"55101002900"}},{"type":"Polygon","arcs":[[-83,-26,-27,-61,-43]],"properties":{"GEOID":"55101001401"}},{"type":"Polygon","arcs":[[105,106,107,108,-96,109,110,111]],"properties":{"GEOID":"55101002002"}},{"type":"Polygon","arcs":[[-28,-24,112,-89,113,-62]],"properties":{"GEOID":"55101001302"}},{"type":"Polygon","arcs":[[-106,114,115]],"properties":{"GEOID":"55101002701"}},{"type":"Polygon","arcs":[[116,-115,-112,117,-100,-1,-97,118]],"properties":{"GEOID":"55101002702"}},{"type":"Polygon","arcs":[[-111,119,120,-80,121,-101,-118]],"properties":{"GEOID":"55101002100"}},{"type":"Polygon","arcs":[[122,-108,123]],"properties":{"GEOID":"55101002001"}},{"type":"Polygon","arcs":[[-63,-114,-92,-37,-84,-103,-15]],"properties":{"GEOID":"55101001202"}},{"type":"Polygon","arcs":[[-124,-107,-116,-117,124]],"properties":{"GEOID":"55101002800"}},{"type":"Polygon","arcs":[[125,-72,-105]],"properties":{"GEOID":"55101000200"}},{"type":"Polygon","arcs":[[-81,-121]],"properties":{"GEOID":"55101980000"}},{"type":"Polygon","arcs":[[-95,-76,126,-78,-120,-110]],"properties":{"GEOID":"55101001802"}},{"type":"Polygon","arcs":[[-51,127,128,-87]],"properties":{"GEOID":"55101000904"}},{"type":"Polygon","arcs":[[-50,-69,129,-128]],"properties":{"GEOID":"55101000903"}}]}},"arcs":[[[12727,42645],[1,-136],[4,-494],[-18,-473],[-163,-1428],[-80,-629],[-211,-843],[-277,-615]],[[11983,38027],[-197,-379],[-506,-984],[366,69],[405,-142],[1105,-1060],[213,-498],[-33,-525],[-19,-248],[-413,285],[-927,-190],[-85,-166],[-90,-1455],[286,-630],[44,-2892],[48,-556],[-187,-736],[523,-2241],[-3189,-695],[-142,-32],[-1152,-253],[-82,-18],[-105,-22],[-221,-49],[-2551,-11],[-150,-28],[-275,-132],[-419,-436]],[[4230,24003],[50,383],[165,1230],[330,2387],[52,364],[663,1263],[63,172],[109,295],[166,234],[29,34],[265,464],[158,1029],[1455,3096],[928,2011],[692,1208],[2936,3889],[436,583]],[[84132,47308],[201,1095],[70,383],[13,71],[120,651],[642,-45],[121,-15],[17,-2],[363,-5],[105,-19],[1130,9],[2,-420],[677,7],[-2,419],[678,11],[225,3],[170,-282]],[[88664,49169],[696,-1159],[41,0],[3,-1005]],[[89404,47005],[-663,-8],[-238,-3],[-900,-10]],[[87603,46984],[-1131,-17],[-671,-10]],[[85801,46957],[-58,5],[-553,38],[4,-657],[-504,35],[-304,21],[-416,30]],[[83970,46429],[47,252],[115,627]],[[96169,79891],[28,-41],[468,-694],[465,-690],[782,-878],[405,-455],[1682,-3541],[-20,-221],[-74,-826],[-162,-213],[-349,-460],[-14,-18],[-594,-280],[-1209,-2351],[-443,-862],[-4,-13]],[[97130,68348],[-1493,24],[-17,0],[-584,2],[-312,1]],[[94724,68375],[13,1168],[4,376],[7,616],[44,4075],[41,3506],[72,131],[713,712],[551,932]],[[78211,62321],[388,-12],[2186,-72],[1357,-53],[1791,-65],[536,-18],[836,-240],[421,-23]],[[85726,61838],[794,-408],[460,-234],[559,-284],[320,-258]],[[87859,60654],[-453,-1125],[-1436,-2183],[-224,-967],[-31,-368],[-334,-1895]],[[85381,54116],[-1397,137]],[[83984,54253],[-1781,300],[0,8],[-1144,289],[-844,250],[-1113,308],[-462,22],[-380,-53]],[[78260,55377],[-34,4939],[-2,221],[-13,1784]],[[87603,46984],[6,-1409],[3,-763],[7,-1759],[4,-1223]],[[87623,41830],[-1792,-456]],[[85831,41374],[-3,1014],[-2,635],[-3,562],[-8,1198],[-4,762],[-10,1412]],[[93828,68382],[896,-7]],[[97130,68348],[-314,-1180],[-280,-1050],[-36,-135],[-184,-688],[-9,-78],[-159,-1344],[-73,-621],[-128,-1083]],[[95947,62169],[-115,-23],[-1147,3]],[[94685,62149],[-37,0],[-857,-4]],[[93791,62145],[108,1254],[7,304],[-1,1559],[5,0],[-95,359],[-5,1193],[18,1568]],[[92046,62134],[853,8],[463,2],[429,1]],[[94685,62149],[3,-1070],[2,-708],[5,-1546],[-282,-3],[-387,-5],[-186,-2],[3,-848],[-465,-5],[-580,-8],[-299,4]],[[92499,57958],[-218,1877],[-235,2299]],[[82755,99435],[2239,-76],[2423,44],[170,-1131],[312,-2081],[2203,-5335],[224,-462],[1549,-3209],[1543,-3194]],[[93418,83991],[-317,-7]],[[93101,83984],[-1359,35],[-452,11],[-25,-414],[-1809,37],[-40,-2702],[-610,-38]],[[88806,80913],[-1271,6153],[-1358,-117],[-299,-25]],[[85878,86924],[8,978],[-296,946],[-37,1955],[-375,2384],[-615,2354],[-950,2208],[-858,1686]],[[85831,41374],[-13,-2],[-2795,-551]],[[83023,40821],[12,63],[24,132],[135,614],[53,310],[74,582],[108,833],[34,212],[111,642],[124,707],[108,612],[164,901]],[[91596,52058],[263,224],[-145,727],[329,544],[565,-1]],[[92608,53552],[0,-968],[37,-717],[275,-2397],[87,-866]],[[93007,48604],[0,-89],[44,-484],[43,-516],[59,-633],[31,-639],[-9,-642],[-146,-1925],[-39,-590]],[[92990,43086],[-600,-286],[-1,244],[-201,-3],[-993,-118]],[[91195,42923],[130,727],[140,775],[23,1],[453,87],[-216,1221],[101,554],[-455,75],[-434,-4],[-692,-6],[508,768],[36,513],[527,1838],[100,0],[-102,424],[130,1588],[237,402],[-85,172]],[[93101,83984],[-67,-6250],[-35,-3121],[-66,-6225]],[[92933,68388],[-1096,2],[-409,1],[-47,0]],[[91381,68391],[-1285,6267],[-713,3453],[-577,2802]],[[82486,37229],[227,1663],[310,1929]],[[87623,41830],[680,141],[1114,254]],[[89417,42225],[2,-522]],[[89419,41703],[2,-695],[3,-905],[5,-2204],[1,-917]],[[89430,36982],[-58,-1]],[[89372,36981],[-1736,-19],[-227,-1],[-656,-1],[-58,0],[-388,-2],[-113,0],[-54,0],[-295,-1]],[[85845,36957],[-1775,151],[-1154,90],[-244,17],[-186,14]],[[85801,75123],[19,3915],[5,1676],[34,3380],[10,1471],[5,656],[4,703]],[[91381,68391],[-2963,-29],[-8,-1058],[-122,515],[-986,-149],[221,971],[43,492],[28,120],[-1831,-25]],[[85763,69228],[38,5212],[-3,186],[3,497]],[[83984,54253],[18,-5184],[2,-258],[-3,-1327],[131,-176]],[[83970,46429],[-1729,120],[-317,9],[-1019,27],[-2233,64],[-355,-119]],[[78317,46530],[-57,8847]],[[78317,46530],[-43,-1191],[-368,-5594],[-57,-12],[-138,-2432],[-394,-6169],[26,-1],[-400,-6216]],[[76943,24915],[-1842,56],[-133,5],[-1788,44],[-1847,54]],[[71333,25074],[214,3105],[4,3149],[-33,6243],[-3,748],[-10,2373],[-16,6248],[126,-11],[1504,-105],[179,-8],[450,-21],[1349,-129],[2680,-116],[540,-20]],[[91381,68391],[173,-1531],[308,-3151],[184,-1575]],[[92499,57958],[54,-660]],[[92553,57298],[-782,670],[-7,6],[-636,564],[-906,790],[-229,201],[-1231,973],[-472,-344],[-136,157],[-179,206],[-24,28],[-92,105]],[[85726,61838],[-2,226],[14,2711],[19,3495],[2,221],[4,737]],[[64738,99972],[3433,-226],[3443,-128],[716,41],[2967,-20],[1496,-45],[3846,-101],[2116,-58]],[[85801,75123],[-588,-80],[-419,-383],[-237,-106],[-2357,101],[-1643,44],[-33,1],[-669,21],[-1741,55],[78,-9327],[7,-1129],[7,-1114],[5,-885]],[[78211,62321],[-1988,77],[-327,18],[-92,-9],[-1783,74],[-318,14],[-400,28],[-436,-17],[-1263,44],[-3716,125],[-3466,116]],[[64422,62791],[66,9316],[28,3139],[19,2147],[15,1777],[51,5444],[138,13180],[-1,2178]],[[88313,24484],[936,6170],[11,73],[77,1082],[30,2036],[-6,1503],[-2,846],[13,787]],[[89430,36982],[894,18],[317,6],[578,12],[680,5],[126,2],[323,3],[600,5],[75,0],[-10,1855],[294,-4],[-3,635],[-4,637]],[[93300,40156],[736,13],[283,5]],[[94319,40174],[989,79]],[[95308,40253],[-30,-190],[-216,-1401],[-309,-43],[-57,-331],[-254,-1474],[-267,-651],[-303,-740],[-352,-859],[-239,-585],[-57,-321],[-321,-1827],[-70,-397],[-45,-261],[-998,-3422],[-10,-68],[-448,-2866],[-47,-301],[-656,-35],[-1419,-4],[-897,7]],[[64360,62792],[62,-1]],[[71333,25074],[-6807,162],[-39,0]],[[64487,25236],[-69,12529],[-23,14909],[-25,3863],[-10,6255]],[[89404,47005],[1,-658],[2,-752],[3,-763],[3,-1200],[2,-726],[2,-681]],[[43067,38098],[1288,686],[2192,1303],[3577,1550],[1036,323],[764,240],[-3,-4485],[-12,-3493],[-42,-4034],[-1,-871],[-796,-11],[20,-4042]],[[51090,25264],[-546,5],[-536,7],[-6903,42]],[[43105,25318],[-10,2952],[-1,153],[24,1],[-14,1029],[-1,82],[1,856],[-9,1139],[-4,799]],[[43091,32329],[-24,5769]],[[93418,83991],[26,-54],[571,-848],[962,-1427],[371,-552],[821,-1219]],[[93828,68382],[-231,2],[-664,4]],[[88495,51905],[168,-97],[38,-22],[137,-76],[560,-313],[224,-132],[423,-70],[103,57],[1070,653],[378,153]],[[91195,42923],[-35,-192],[-118,-535],[-732,-10],[1,-472],[-892,-11]],[[88664,49169],[-2,540],[-5,1280],[-162,916]],[[82486,37229],[-6,-46],[-248,-1878],[-4,-1190],[-33,-2544],[-55,-612],[-212,-1550],[-376,-1616],[-634,-1820],[-192,-1200]],[[80726,24773],[-954,36],[-1378,46],[-1451,60]],[[92607,55699],[317,-1],[251,3],[461,6],[216,3],[7,0],[847,-19],[771,10],[131,2],[359,37]],[[95967,55740],[39,-185],[114,-539],[23,-252],[25,-275],[46,-500],[84,-916],[16,-170],[-12,-37],[-51,-164]],[[96251,52702],[-1086,28],[-321,-108],[55,-721],[120,-968],[-167,-515],[-171,-96],[-700,736],[-319,-340],[-494,-979],[-161,-1135]],[[92608,53552],[32,1626],[-33,521]],[[92990,43086],[11,-132],[-48,-660],[17,-722],[323,9],[7,-1425]],[[43285,99876],[5263,52],[1750,22],[146,1],[2442,27],[2873,15],[3535,6],[109,0],[5335,-27]],[[64360,62792],[-2665,33],[-8930,67],[-2567,5],[-3692,-27],[-1765,-30],[-1790,3]],[[42951,62843],[77,9276],[37,4663],[60,6884],[6,657],[2,237],[28,3097],[124,12219]],[[220,43535],[6754,47],[3959,28],[774,4],[238,6],[774,9],[8,-984]],[[4230,24003],[-533,-490],[-1099,-1085],[-2284,-1477]],[[314,20951],[42,1304],[34,1041],[4,1027],[0,209],[0,55],[1,295],[-15,1231],[-14,2182],[-52,3149],[-61,2739],[-18,1408],[-10,1733],[-10,1770],[5,4441]],[[11983,38027],[1688,-352],[448,-236],[429,-13],[1919,29],[2542,42],[2662,48]],[[21671,37545],[43,-6213],[53,-6034]],[[21767,25298],[0,-10812],[25,-14212],[-6769,-118],[-50,0],[-7412,-53],[-14,1],[-588,-2],[-2992,-15],[-1606,-63],[-1353,-18],[-614,-6],[-36,12494],[-8,1490],[-16,3106],[-20,3861]],[[85381,54116],[382,-26],[1180,-468],[254,-275],[391,-463],[483,-584],[346,-325],[78,-70]],[[96251,52702],[-79,-250],[-137,-437],[-134,-428],[-88,-282],[280,-845],[141,-424],[17,-568]],[[96251,49468],[-1359,-10],[-480,-28],[-135,-98],[5,-1159],[3,-640],[5,-1277],[3,-641],[2,-641],[206,3],[5,-1281],[-205,-3],[4,-725],[7,-1376],[7,-1418]],[[21525,65714],[35,3529]],[[21560,69243],[54,4273]],[[21614,73516],[195,662],[301,783],[3312,7929],[147,405],[490,1764],[42,175],[203,998],[154,695],[86,639],[383,2727],[522,2914],[205,655],[3,8],[129,314],[3232,5589]],[[31018,99773],[563,16],[945,39],[752,25],[246,-21],[390,5],[4861,34],[34,0],[3910,4],[566,1]],[[42951,62843],[0,-22]],[[42951,62821],[-1548,16],[-223,-2],[-1770,-6],[-3610,-44],[-5374,-100],[-452,-10],[-6883,-64],[-822,-12],[-768,-10]],[[21501,62589],[24,3125]],[[95947,62169],[-278,-2358],[23,-2763],[275,-1308]],[[92607,55699],[-17,774],[-37,825]],[[21525,65714],[-836,-13],[-425,-156],[-362,-143],[-76,-30],[-91,-34],[-1311,-6],[-1116,-9],[-115,59],[-436,260],[-553,485],[-614,1173],[-363,697],[-138,192],[-58,58],[-621,299]],[[14410,68546],[6,950],[0,41],[31,2200],[8,718],[10,840],[3,235],[43,3594],[1316,1713],[106,39],[-152,-975],[82,-37],[48,328],[47,85],[89,48],[47,-251],[13,-661],[294,-1450],[61,-668],[-57,-1533],[-150,-1321],[52,-212],[283,-122],[317,273],[942,-24],[129,131],[29,-679],[942,28],[-53,-180],[13,-1139],[896,41],[9,579],[96,-232],[229,-434],[173,-256],[184,-221],[183,-171],[56,-45],[58,-42],[767,-493]],[[45,62145],[5334,61],[1170,18],[608,15],[7156,127],[1,1386],[96,4794]],[[21501,62589],[17,-2489],[39,-5409],[23,-3167],[6,-1481],[1,-49],[29,-6243],[55,-6206]],[[220,43535],[20,689],[-76,2422],[-119,15499]],[[42951,62821],[14,-2564],[23,-3839],[18,-6216],[14,-4699],[4,-1524],[43,-5881]],[[43067,38098],[-733,-377],[-2544,-21],[-229,-236],[-106,-486],[38,-5070],[328,-284],[3270,705]],[[43105,25318],[-682,-8],[-1014,-11],[-106,-1],[-571,84],[-3958,-103],[-853,-114],[-10641,-125],[-3513,258]],[[21820,99669],[808,5],[2733,27],[899,-22],[465,0],[4221,91],[72,3]],[[21614,73516],[13,1412],[17,1511],[41,3783],[65,8166],[57,5238],[13,3104],[0,2939]],[[45,62145],[-45,0],[13,555],[76,9160],[-5,191],[19,2513],[61,5940],[14,3364],[26,6218],[2,448],[64,6635],[25,1570],[10,610],[3700,-10],[6192,-39],[1143,9],[2856,67],[204,-98],[1384,77],[1522,107],[2708,152],[1791,55],[15,0]],[[96251,49468],[72,-2341],[22,-694],[-505,-367],[-4,-3],[-1,-18],[-223,-3323],[-59,-882],[-48,-311],[-197,-1273],[0,-3]],[[64487,25236],[-25,1],[-5358,-10],[-3529,-1],[-4485,38]],[[85845,36957],[1,-1032],[0,-286],[0,-387],[1,-96],[0,-565],[0,-45],[0,-336],[0,-234],[0,-592],[-1,-1277],[-1,-1382],[-3,-1587],[0,-11],[-14,-4630]],[[85828,24497],[-323,19],[-1514,89],[-3265,168]],[[88313,24484],[-2485,13]]],"bbox":[-88.30806,42.610817,-87.757913,42.843609],"transform":{"scale":[0.000005501525015250107,0.0000023279432794328285],"translate":[-88.30806,42.610817]}}